cdktf_cdktf_provider_postgresql/__init__.py
cdktf_cdktf_provider_postgresql/py.typed
cdktf_cdktf_provider_postgresql/_jsii/__init__.py
cdktf_cdktf_provider_postgresql/_jsii/provider-postgresql@12.1.0.jsii.tgz
cdktf_cdktf_provider_postgresql/data_postgresql_schemas/__init__.py
cdktf_cdktf_provider_postgresql/data_postgresql_sequences/__init__.py
cdktf_cdktf_provider_postgresql/data_postgresql_tables/__init__.py
cdktf_cdktf_provider_postgresql/database/__init__.py
cdktf_cdktf_provider_postgresql/default_privileges/__init__.py
cdktf_cdktf_provider_postgresql/extension/__init__.py
cdktf_cdktf_provider_postgresql/function_resource/__init__.py
cdktf_cdktf_provider_postgresql/grant/__init__.py
cdktf_cdktf_provider_postgresql/grant_role/__init__.py
cdktf_cdktf_provider_postgresql/physical_replication_slot/__init__.py
cdktf_cdktf_provider_postgresql/provider/__init__.py
cdktf_cdktf_provider_postgresql/publication/__init__.py
cdktf_cdktf_provider_postgresql/replication_slot/__init__.py
cdktf_cdktf_provider_postgresql/role/__init__.py
cdktf_cdktf_provider_postgresql/schema/__init__.py
cdktf_cdktf_provider_postgresql/security_label/__init__.py
cdktf_cdktf_provider_postgresql/server/__init__.py
cdktf_cdktf_provider_postgresql/subscription/__init__.py
cdktf_cdktf_provider_postgresql/user_mapping/__init__.py
cdktf_cdktf_provider_postgresql-12.1.0.dist-info/LICENSE
cdktf_cdktf_provider_postgresql-12.1.0.dist-info/METADATA
cdktf_cdktf_provider_postgresql-12.1.0.dist-info/WHEEL
cdktf_cdktf_provider_postgresql-12.1.0.dist-info/top_level.txt
cdktf_cdktf_provider_postgresql-12.1.0.dist-info/RECORD
